sxs/__init__.py
sxs/__version__.py
sxs/citation.py
sxs/handlers.py
sxs/juliapkg.json
sxs/time_series.py
sxs/catalog/__init__.py
sxs/catalog/catalog.py
sxs/catalog/create.py
sxs/catalog/description.py
sxs/horizons/__init__.py
sxs/horizons/spec_horizons_h5.py
sxs/horizons/xor_multishuffle_bzip2.py
sxs/julia/GWFrames.py
sxs/julia/__init__.py
sxs/metadata/__init__.py
sxs/metadata/metadata.py
sxs/metadata/metric.py
sxs/simulations/__init__.py
sxs/simulations/analyze.py
sxs/simulations/local.py
sxs/simulations/simulation.py
sxs/simulations/simulations.py
sxs/utilities/__init__.py
sxs/utilities/bitwise.py
sxs/utilities/dicts.py
sxs/utilities/downloads.py
sxs/utilities/files.py
sxs/utilities/formats.py
sxs/utilities/inspire.py
sxs/utilities/monotonicity.py
sxs/utilities/pretty_print.py
sxs/utilities/select.py
sxs/utilities/smooth_functions.py
sxs/utilities/string_converters.py
sxs/utilities/sxs_directories.py
sxs/utilities/sxs_identifiers.py
sxs/utilities/url.py
sxs/utilities/decimation/__init__.py
sxs/utilities/decimation/greedy_spline.py
sxs/utilities/decimation/linear_bisection.py
sxs/utilities/decimation/peak_greed.py
sxs/utilities/decimation/suppression.py
sxs/utilities/lvcnr/__init__.py
sxs/utilities/lvcnr/comparisons.py
sxs/utilities/lvcnr/conversion.py
sxs/utilities/lvcnr/dataset.py
sxs/utilities/lvcnr/horizons.py
sxs/utilities/lvcnr/metadata.py
sxs/utilities/lvcnr/waveform_amp_phase.py
sxs/utilities/lvcnr/waveforms.py
sxs/utilities/references/__init__.py
sxs/utilities/references/ads.py
sxs/utilities/references/arxiv.py
sxs/utilities/references/fairchild_report.py
sxs/utilities/references/inspire.py
sxs/utilities/references/journal_abbreviations.py
sxs/utilities/references/references.py
sxs/waveforms/__init__.py
sxs/waveforms/alignment.py
sxs/waveforms/memory.py
sxs/waveforms/mode_utilities.py
sxs/waveforms/norms.py
sxs/waveforms/transformations.py
sxs/waveforms/waveform_grid.py
sxs/waveforms/waveform_mixin.py
sxs/waveforms/waveform_modes.py
sxs-2025.0.22.dist-info/METADATA
sxs-2025.0.22.dist-info/WHEEL
sxs-2025.0.22.dist-info/entry_points.txt
sxs-2025.0.22.dist-info/licenses/LICENSE
sxs-2025.0.22.dist-info/RECORD
