Metadata-Version: 2.4
Name: sxs
Version: 2025.0.22
Summary: Interface to data produced by the Simulating eXtreme Spacetimes collaboration
Project-URL: Homepage, https://github.com/sxs-collaboration/sxs
Project-URL: Documentation, https://sxs.readthedocs.io/
Author-email: Michael Boyle <michael.oliver.boyle@gmail.com>
License-Expression: MIT
License-File: LICENSE
Classifier: Development Status :: 5 - Production/Stable
Classifier: Intended Audience :: Science/Research
Classifier: Operating System :: OS Independent
Classifier: Programming Language :: Python :: 3
Classifier: Topic :: Scientific/Engineering :: Astronomy
Classifier: Topic :: Scientific/Engineering :: Physics
Requires-Python: >=3.10
Requires-Dist: bibtexparser>=2.0.0b8
Requires-Dist: h5py>=3
Requires-Dist: inflection>=0.5.1
Requires-Dist: juliacall>=0.9.30
Requires-Dist: numba>=0.55; implementation_name == 'cpython'
Requires-Dist: numpy<3.0,>=2.0
Requires-Dist: packaging
Requires-Dist: pandas>=1.1.2
Requires-Dist: pytz>=2020.1
Requires-Dist: quaternionic>=1.0.15
Requires-Dist: requests>=2.24.0
Requires-Dist: scipy>=1.13
Requires-Dist: spherical>=1.0.15
Requires-Dist: sxscatalog>=3.0.14
Requires-Dist: tqdm>=4.63.1
Requires-Dist: urllib3>=1.25.10
Provides-Extra: docs
Requires-Dist: mkdocs; extra == 'docs'
Requires-Dist: mkdocs-jupyter; extra == 'docs'
Requires-Dist: mkdocs-material; extra == 'docs'
Requires-Dist: mkdocstrings-python; extra == 'docs'
Provides-Extra: ecosystem
Requires-Dist: ipykernel>=6.29; extra == 'ecosystem'
Requires-Dist: ipywidgets>=8.0; extra == 'ecosystem'
Requires-Dist: jupyterlab>=4.2; extra == 'ecosystem'
Requires-Dist: line-profiler>=3.0.2; extra == 'ecosystem'
Requires-Dist: matplotlib>=2.1.1; extra == 'ecosystem'
Requires-Dist: memory-profiler>=0.57.0; extra == 'ecosystem'
Requires-Dist: numpy-quaternion>=2023.0.4; extra == 'ecosystem'
Requires-Dist: numpy<3.0,>=2.0; extra == 'ecosystem'
Requires-Dist: qgridnext>=2.0; extra == 'ecosystem'
Requires-Dist: rise>=5.6.1; extra == 'ecosystem'
Requires-Dist: scri>=2020.8.18; (sys_platform != 'win32') and extra == 'ecosystem'
Requires-Dist: seaborn>=0.13; extra == 'ecosystem'
Requires-Dist: spinsfast>=2022; (sys_platform != 'win32') and extra == 'ecosystem'
Requires-Dist: sympy>=1.6.2; extra == 'ecosystem'
